fishhook/__init__.py
fishhook/_asm.cpython-313-x86_64-linux-gnu.so
fishhook/_asmmodule.c
fishhook/asm.py
fishhook/fishhook.py
fishhook/jit.py
fishhook/tests.py
fishhook-0.3.5.dist-info/METADATA
fishhook-0.3.5.dist-info/WHEEL
fishhook-0.3.5.dist-info/top_level.txt
fishhook-0.3.5.dist-info/RECORD
fishhook-0.3.5.dist-info/licenses/LICENSE
