Metadata-Version: 2.1
Name: fishhook
Version: 0.3.5
Summary: Allows for runtime hooking of static class functions
Author-email: chilaxan <chilaxan@gmail.com>
License: MIT
Project-URL: repository, https://github.com/chilaxan/fishhook
Classifier: Programming Language :: Python :: 3
Classifier: License :: OSI Approved :: MIT License
Classifier: Operating System :: OS Independent
Requires-Python: >=3.8
License-File: LICENSE
Requires-Dist: capstone ; os_name != "nt"
Requires-Dist: keystone-engine ; os_name != "nt"
